ee_multi/__init__.py
ee_multi/distributor.py
ee_multi-0.1.0.dist-info/METADATA
ee_multi-0.1.0.dist-info/WHEEL
ee_multi-0.1.0.dist-info/top_level.txt
ee_multi-0.1.0.dist-info/RECORD
